adt_core/__init__.py
adt_core/__main__.py
adt_core/cli.py
adt_core/exceptions.py
adt_core/module_sequencer.py
adt_core-2.0.1.dist-info/licenses/LICENSE
adt_core-2.0.1.dist-info/METADATA
adt_core-2.0.1.dist-info/WHEEL
adt_core-2.0.1.dist-info/entry_points.txt
adt_core-2.0.1.dist-info/top_level.txt
adt_core-2.0.1.dist-info/RECORD
