Metadata-Version: 2.4
Name: adt-core
Version: 2.0.1
Summary: ADT Module Configuration and Sequencing System
Requires-Python: >=3.8
License-File: LICENSE
Requires-Dist: importlib-metadata>=1.0; python_version < "3.8"
Provides-Extra: dev
Requires-Dist: pytest>=6.0; extra == "dev"
Requires-Dist: pytest-cov>=2.0; extra == "dev"
Requires-Dist: black>=21.0; extra == "dev"
Requires-Dist: flake8>=3.8; extra == "dev"
Dynamic: license-file
